coders/__init__.py
tests/__init__.py
tests/test_coders.py
py_coders-1.1.5.dist-info/LICENSE
py_coders-1.1.5.dist-info/METADATA
py_coders-1.1.5.dist-info/WHEEL
py_coders-1.1.5.dist-info/top_level.txt
py_coders-1.1.5.dist-info/RECORD
