Metadata-Version: 2.1
Name: py-coders
Version: 1.1.5
Summary: A simple set of symmetric encoder/decoder classes for serializing to and from bytearrays.
Home-page: https://github.com/james7132/py-coders
Author: James Liu
Author-email: contact@jamessliu.com
License: UNKNOWN
Platform: UNKNOWN
Classifier: Programming Language :: Python :: 3
Classifier: Programming Language :: Python :: 3.6
Classifier: Programming Language :: Python :: 3.7
Classifier: Programming Language :: Python :: 3.8
Classifier: License :: OSI Approved :: MIT License
Classifier: Operating System :: OS Independent
